{
  "id": "BTI-20250514080116",
  "timestamp": "20250514080116",
  "date": "2025-05-14",
  "recommendation": "一、市场周期分析  \n当前比特币价格在104,100美元附近震荡，近30日波动区间为84,000-105,000美元。AHR999指标1.0877处于估值合理区间（历史极值：2024-12-17达1.7504），恐惧贪婪指数73显示市场情绪偏贪婪但未达极端（历史峰值84）。价格在100,500美元形成强支撑，105,000美元存在明显阻力。综合判断市场处于分配期，高位震荡中酝酿方向选择。\n\n二、技术指标解读  \n1. 价格趋势：30日价格在100,000-105,000美元箱体震荡，短期均线（7日）与长期均线（30日）粘合，成交量连续两周萎缩  \n2. 市场估值：当前AHR999处于近半年50%分位，恐惧贪婪指数高于半年均值（59）但低于牛市峰值（94），显示中性偏乐观估值  \n3. 周期阶段：距离历史最高价（106,143）回撤2%，未出现恐慌抛售，符合分配期特征\n\n三、投资决策建议  \n1. 仓位调整：从75%降至65%（减持10%）  \n2. 入场/出场价位：  \n   - 减仓区间：104,500-105,200美元（当前价格附近）  \n   - 补仓区间：99,800-101,000美元（需配合放量）  \n3. 止损设置：  \n   - 硬止损99,800（保护成本基础）  \n   - 动态止损跌破100,500后启动  \n4. 获利目标：  \n   - 短期（3个月）：112,000美元（突破前高后7%涨幅）  \n   - 中期（12个月）：138,000美元（基于减半周期历史均值）\n\n四、仓位管理追踪  \n本次建议：减持10%锁定利润，保留65%核心仓位  \n新成本基础：82,278美元（未改变，因减持高位仓位）  \n预期回报率：现价至中期目标潜在回报率32.6%\n\n五、风险分析  \n1. 突破失败风险：连续3日收于105,000下方可能引发回调 → 触发止损后保留50%现金  \n2. 情绪逆转风险：恐惧贪婪指数>80时强制启动5%阶梯减仓  \n3. 黑天鹅风险：单日跌幅>8%时暂停所有操作直至波动率恢复正常  \n\n六、未来观察指标  \n1. 105,300美元阻力位：连续2小时站上则加仓5%  \n2. 周线RSI(14)>85：触发自动减持10%  \n3. 矿工持仓指数：若30日净流出>5万BTC，启动防御策略  \n\n```json\n{\n  \"date\": \"2025-05-14\",\n  \"position\": 65,\n  \"position_change\": \"减少10%\",\n  \"action\": \"减仓\",\n  \"entry_price\": \"104,500-105,200\",\n  \"stop_loss\": 99800,\n  \"target_short\": 112000,\n  \"target_mid\": 138000,\n  \"cost_basis\": 82278,\n  \"expected_return\": \"32.6%\",\n  \"market_cycle\": \"分配期\",\n  \"risks\": [\"突破失败回调\",\"情绪过热修正\",\"矿工抛压加剧\"],\n  \"key_levels\": [\"105,300突破位\",\"100,500支撑位\",\"98,000强支撑\"]\n}\n```",
  "advice_data": {
    "date": "2025-05-14",
    "position": 65,
    "position_change": "减少10%",
    "action": "减仓",
    "entry_price": "104,500-105,200",
    "stop_loss": 99800,
    "target_short": 112000,
    "target_mid": 138000,
    "cost_basis": 82278,
    "expected_return": "32.6%",
    "market_cycle": "分配期",
    "risks": [
      "突破失败回调",
      "情绪过热修正",
      "矿工抛压加剧"
    ],
    "key_levels": [
      "105,300突破位",
      "100,500支撑位",
      "98,000强支撑"
    ]
  },
  "metadata": {
    "last_record_id": "BTI-20250513080215",
    "user_settings": {}
  }
}