{
  "id": "BTI-20250503080134",
  "timestamp": "20250503080134",
  "date": "2025-05-03",
  "recommendation": "一、市场周期分析  \n当前比特币价格96,887美元处于2月高点（106,143美元）回调后的反弹阶段。AHR999指标0.975接近估值中枢（1.0），恐惧贪婪指数65显示中性情绪。关键支撑位93,000美元（4月震荡中枢），阻力位98,000美元（3月压力位）。市场处于从分配期向积累期过渡阶段，未出现明显过热信号。\n\n二、技术指标解读  \n1. 价格趋势：30日涨幅16%，形成上升通道，但连续4日在96,500美元附近缩量震荡，需突破98,000美元确认趋势延续  \n2. 市场估值：AHR999较1月高点1.75回落45%，处近6个月中位数（1.02）下方，估值回归合理区间  \n3. 周期阶段：中期调整后的技术性反弹，尚未进入明确上升周期  \n\n三、投资决策建议  \n1. 仓位调整：维持60%仓位，保留40%现金等待突破确认  \n2. 入场/出场价位：  \n   - 突破加仓：98,200-99,500美元区间分批买入30%预算（300美元）  \n   - 回调买入：93,000-94,500美元区间投入剩余70%预算（700美元）  \n3. 止损设置：全仓止损89,500美元，若触发则等待85,000美元重新建仓  \n4. 获利目标：  \n   - 短期（3个月）：105,000美元（触及后减仓20%）  \n   - 中期（6个月）：122,000美元（触及后减仓至30%）  \n\n四、仓位管理追踪  \n上次建议：仓位60% | 本次建议：维持60%  \n新成本基础：80,327美元（未新增持仓）  \n预期回报率：现价至中期目标+25.9%（不含杠杆）  \n\n五、风险分析  \n1. 假突破风险：若价格突破98k后快速回落至95k下方，立即平掉新增仓位  \n2. 流动性风险：恐惧贪婪指数>75时，启动10%自动减仓机制  \n3. 黑天鹅风险：单日跌幅>12%时，当日暂停所有交易操作  \n\n六、未来观察指标  \n1. AHR999突破1.15：估值进入危险区间，启动每月5%定期减仓  \n2. 周线收于89,500下方：确认趋势反转，仓位降至30%  \n3. 交易所净流入>3万BTC/周：链上抛压信号，启动对冲操作  \n\n```json\n{\n  \"date\": \"2025-05-03\",\n  \"position\": 60,\n  \"position_change\": \"维持0%\",\n  \"action\": \"持有\",\n  \"entry_price\": \"93,000-94,500或突破98,200\",\n  \"stop_loss\": 89500,\n  \"target_short\": 105000,\n  \"target_mid\": 122000,\n  \"cost_basis\": 80327,\n  \"expected_return\": \"25.9%\",\n  \"market_cycle\": \"积累期\",\n  \"risks\": [\"假突破风险\", \"流动性收缩\", \"监管政策变化\"],\n  \"key_levels\": [\"93500\", \"98200\", \"105000\"]\n}\n```",
  "advice_data": {
    "date": "2025-05-03",
    "position": 60,
    "position_change": "维持0%",
    "action": "持有",
    "entry_price": "93,000-94,500或突破98,200",
    "stop_loss": 89500,
    "target_short": 105000,
    "target_mid": 122000,
    "cost_basis": 80327,
    "expected_return": "25.9%",
    "market_cycle": "积累期",
    "risks": [
      "假突破风险",
      "流动性收缩",
      "监管政策变化"
    ],
    "key_levels": [
      "93500",
      "98200",
      "105000"
    ]
  },
  "metadata": {
    "last_record_id": "BTI-20250502080618",
    "user_settings": {}
  }
}