{
  "id": "BTI-20250422080106",
  "timestamp": "20250422080106",
  "date": "2025-04-22",
  "recommendation": "一、市场周期分析  \n当前价格在84k-90k区间震荡，AHR999(0.82)处于估值合理区间，恐惧贪婪指数47显示中性情绪。关键支撑位79,500（前低+历史止损位），阻力位89,300（3月高位）。市场处于牛市中继阶段的积累期，尚未突破前高但已脱离底部区间，成交量萎缩显示多空博弈。\n\n二、技术指标解读  \n1. 价格趋势：价格在84k-88k形成箱体震荡，50日均线（约84,200）提供支撑，量能持续萎缩需突破确认方向  \n2. 市场估值：AHR999较2025年1月高点1.6已回落48%，处于牛市中场合理估值区间。恐惧贪婪指数从极端贪婪(84)回调至中性，市场过热风险释放  \n3. 周期阶段：从分配期（1月AHR999>1.2）过渡至积累期，尚未出现明确上升趋势信号  \n\n三、投资决策建议  \n1. 仓位调整：维持75%仓位，保留25%现金等待突破确认  \n2. 入场/出场价位：突破89,300追涨加仓10%，跌破80,000减仓15%。分批建仓区间85,000-87,500  \n3. 止损设置：动态止损上移至80,000（较当前价-8.6%），跌破后若3日未收复则触发止损  \n4. 获利目标：短期目标93,000（+6.3%），中期目标112,000（+28%），达到短期目标后减持10%锁定利润  \n\n四、仓位管理追踪  \n上次建议：75%仓位@87,200，止损79,500  \n本次建议：维持仓位，优化止损  \n仓位变化：75% → 75%（若触发突破加仓则至85%）  \n新成本基础：78,214（未变化）  \n预期回报率：中期28%（基于112k目标）  \n\n五、风险分析  \n1. 假突破风险：若突破89k后量能不足可能回撤 → 加仓部分设置83,500止损  \n2. 流动性紧缩：美股波动可能传导至加密市场 → 监控VIX指数突破25时启动对冲  \n3. 监管风险：关注美国SEC政策变化 → 持仓超过80%时启动10%减仓预案  \n\n六、未来观察指标  \n1. 周线收盘价89,300：有效突破则确认新上涨周期，立即执行追涨  \n2. AHR999突破1.0：估值进入过热区域触发10%减仓  \n3. 恐惧贪婪指数<30：市场恐慌信号出现时启动5%逆势加仓  \n\n```json\n{\n  \"date\": \"2025-04-22\",\n  \"position\": 75,\n  \"position_change\": \"维持0%\",\n  \"action\": \"持有\",\n  \"entry_price\": \"85,000-87,500\",\n  \"stop_loss\": 80000,\n  \"target_short\": 93000,\n  \"target_mid\": 112000,\n  \"cost_basis\": 78214,\n  \"expected_return\": \"28%\",\n  \"market_cycle\": \"积累期\",\n  \"risks\": [\"假突破风险\", \"流动性紧缩\", \"监管政策变化\"],\n  \"key_levels\": [\"79500支撑\", \"89300阻力\", \"112000斐波那契扩展位\"]\n}\n```",
  "advice_data": {
    "date": "2025-04-22",
    "position": 75,
    "position_change": "维持0%",
    "action": "持有",
    "entry_price": "85,000-87,500",
    "stop_loss": 80000,
    "target_short": 93000,
    "target_mid": 112000,
    "cost_basis": 78214,
    "expected_return": "28%",
    "market_cycle": "积累期",
    "risks": [
      "假突破风险",
      "流动性紧缩",
      "监管政策变化"
    ],
    "key_levels": [
      "79500支撑",
      "89300阻力",
      "112000斐波那契扩展位"
    ]
  },
  "metadata": {
    "last_record_id": "BTI-20250421080129",
    "user_settings": {}
  }
}