{
  "id": "BTI-20250510080113",
  "timestamp": "20250510080113",
  "date": "2025-05-10",
  "recommendation": "一、市场周期分析  \n当前市场处于积累期向上升期过渡阶段。关键支撑位94,000美元（历史密集成交区），阻力位105,000美元（前高压力位）。AHR999指标1.0777处于合理估值区间（1.0为牛熊分界线），恐惧贪婪指数70显示市场情绪转向贪婪但未达极端水平。4月低点85,000美元形成的双底结构为中期提供支撑。\n\n二、技术指标解读  \n1. 价格趋势：BTC在5月7日测试97,030美元支撑后形成V型反弹，短期均线（5日）上穿20日均线形成金叉，成交量在突破100,000美元时放大  \n2. 市场估值：当前AHR999较4月低点0.728回升45%，但仍低于2025-01-22峰值1.5294；恐惧贪婪指数70较上周59明显回升  \n3. 周期阶段：价格脱离底部区间但未突破前高，符合积累期尾部特征  \n\n三、投资决策建议  \n1. 仓位调整：维持75%仓位，保留25%现金应对波动  \n2. 入场/出场价位：突破105,000美元加仓10%（使用预算500美元），回调至98,500-99,500区间补仓15%（使用剩余500美元）  \n3. 止损设置：动态止损线上移至97,000美元（较当前价-5.8%），跌破后暂停加仓并在重新站上99,000时恢复  \n4. 获利目标：短期目标110,000（+6.8%），中期目标128,000（+24.3%），达到短期目标后减持10%仓位锁定利润  \n\n四、仓位管理追踪  \n本次建议：维持仓位观察突破，保留现金等待关键价位  \n仓位变化：75% → 75%（未调整）  \n新成本基础：82,278美元（未新增仓位）  \n预期回报率：现价至中期目标潜在回报55.3%（未杠杆）  \n\n五、风险分析  \n1. 假突破风险：若突破105,000后24小时内未能站稳，立即平掉新增仓位  \n2. 流动性收缩：若单日跌幅超7%且恐惧贪婪指数跌破50，启动对冲策略  \n3. 监管黑天鹅：关注110,000美元上方的大额链上转账，异常活动触发5%仓位减持  \n\n六、未来观察指标  \n1. AHR999突破1.2：触发估值预警，启动分批止盈  \n2. 周线收盘低于97,000：确认趋势反转，启动止损程序  \n3. 恐惧贪婪指数>75：触发极端贪婪信号，强制减持10%仓位  \n\n```json\n{\n  \"date\": \"2025-05-10\",\n  \"position\": 75,\n  \"position_change\": \"维持0%\",\n  \"action\": \"持有\",\n  \"entry_price\": \"98,500-99,500(补仓) & 105,000(突破)\",\n  \"stop_loss\": 97000,\n  \"target_short\": 110000,\n  \"target_mid\": 128000,\n  \"cost_basis\": 82278,\n  \"expected_return\": \"55.3%\",\n  \"market_cycle\": \"积累期\",\n  \"risks\": [\"假突破风险\", \"流动性收缩\", \"监管黑天鹅\"],\n  \"key_levels\": [\"94,000支撑\", \"105,000阻力\", \"110,000心理关口\"]\n}\n```",
  "advice_data": {
    "date": "2025-05-10",
    "position": 75,
    "position_change": "维持0%",
    "action": "持有",
    "entry_price": "98,500-99,500(补仓) & 105,000(突破)",
    "stop_loss": 97000,
    "target_short": 110000,
    "target_mid": 128000,
    "cost_basis": 82278,
    "expected_return": "55.3%",
    "market_cycle": "积累期",
    "risks": [
      "假突破风险",
      "流动性收缩",
      "监管黑天鹅"
    ],
    "key_levels": [
      "94,000支撑",
      "105,000阻力",
      "110,000心理关口"
    ]
  },
  "metadata": {
    "last_record_id": "BTI-20250509080126",
    "user_settings": {}
  }
}