{
  "id": "BTI-20250522080120",
  "timestamp": "20250522080120",
  "date": "2025-05-22",
  "recommendation": "一、市场周期分析  \n当前市场处于上升期中期，价格突破前高109,669美元后维持强势。关键支撑位105,000美元（5月19日低点），阻力位112,000美元（心理整数关口）。AHR999指标1.1836处于估值适中区间（低于2025-01-22的1.5294泡沫区），恐惧贪婪指数72显示市场情绪偏贪婪但未达极端。短期存在技术回调需求，但中期趋势未破。\n\n二、技术指标解读  \n1. 价格趋势：7日涨幅6.2%（103,126→109,669），呈现阶梯式上涨，未出现显著放量回调  \n2. 市场估值：AHR999处于近6个月数据的60分位，恐惧贪婪指数较2025-01-22的84高点更理性  \n3. 周期阶段：从2024-11月的积累期（AHR999<0.9）过渡至当前上升期，尚未出现分配期特征  \n\n三、投资决策建议  \n1. 仓位调整：维持60%仓位（当前成本87,639美元，浮盈25.3%），暂停加仓  \n2. 入场/出场价位：突破112,000美元追涨5%仓位，跌破105,000美元减仓至50%  \n3. 止损设置：动态止损上移至105,000美元（较当前价-4.3%），若触发则等待100,000美元重新建仓  \n4. 获利目标：短期115,000（1-3个月，+4.9%），中期130,000（6个月，+18.5%），达目标后分批止盈  \n\n四、仓位管理追踪  \n本次建议：持有观察，动态止损上移  \n仓位变化：60%→60%（维持）  \n新成本基础：87,639美元（未操作）  \n预期回报率：中期目标达成可实现18.5%回报  \n\n五、风险分析  \n1. 贪婪指数突破80风险：若恐惧贪婪值>80，立即减持10%仓位对冲情绪过热  \n2. AHR999快速攀升风险：指标>1.3时启动网格止盈，每上涨2%卖出5%仓位  \n3. 宏观流动性风险：关注美联储利率决议，若实际利率>2%则启动防御性减仓  \n\n六、未来观察指标  \n1. AHR999阈值1.25：突破则启动10%仓位止盈，防止估值泡沫化  \n2. 周线收盘价105,000美元：跌破触发止损并切换至防御策略  \n3. 交易所净流入量：连续3日>2万BTC时视为大户出货信号，需同步减仓  \n\n```json\n{\n  \"date\": \"2025-05-22\",\n  \"position\": 60,\n  \"position_change\": \"维持0%\",\n  \"action\": \"持有\",\n  \"entry_price\": \"112,000突破追涨\",\n  \"stop_loss\": 105000,\n  \"target_short\": 115000,\n  \"target_mid\": 130000,\n  \"cost_basis\": 87639,\n  \"expected_return\": \"18.5%\",\n  \"market_cycle\": \"上升期\",\n  \"risks\": [\"情绪过热风险\",\"估值泡沫风险\",\"流动性收紧风险\"],\n  \"key_levels\": [\"支撑105000\",\"阻力112000\",\"观测阈值AHR9991.25\"]\n}\n```",
  "advice_data": {
    "date": "2025-05-22",
    "position": 60,
    "position_change": "维持0%",
    "action": "持有",
    "entry_price": "112,000突破追涨",
    "stop_loss": 105000,
    "target_short": 115000,
    "target_mid": 130000,
    "cost_basis": 87639,
    "expected_return": "18.5%",
    "market_cycle": "上升期",
    "risks": [
      "情绪过热风险",
      "估值泡沫风险",
      "流动性收紧风险"
    ],
    "key_levels": [
      "支撑105000",
      "阻力112000",
      "观测阈值AHR9991.25"
    ]
  },
  "metadata": {
    "last_record_id": "BTI-20250521080112",
    "user_settings": {}
  }
}